sui_brownie/MANIFEST.in
sui_brownie/README.md
sui_brownie/__init__.py
sui_brownie/account.py
sui_brownie/brownie-config.example.yaml
sui_brownie/ed25519.py
sui_brownie/parallelism.py
sui_brownie/sui_brownie.py
sui_brownie/sui_config.template.yaml
sui_brownie/sui_keystore.template.keystore
sui_brownie/utils.py
sui_brownie-10.5.0.dist-info/METADATA
sui_brownie-10.5.0.dist-info/WHEEL
sui_brownie-10.5.0.dist-info/top_level.txt
sui_brownie-10.5.0.dist-info/RECORD
